chatgptprtk/__init__.py
chatgptprtk/main.py
chatgptprtk/req_call.py
chatgptprtk/server_call.py
chatgptprtk-0.1.3.dist-info/METADATA
chatgptprtk-0.1.3.dist-info/WHEEL
chatgptprtk-0.1.3.dist-info/licenses/LICENSE
chatgptprtk-0.1.3.dist-info/RECORD
