Metadata-Version: 2.1
Name: chatgptprtk
Version: 0.1.3
Summary: A python wrapper around OpenAI ChatGPT for easy access of its functionality
Author-email: Pratik Joshi <pratikjoshi999@gmail.com>
License-File: LICENSE
Classifier: License :: OSI Approved :: MIT License
Classifier: Operating System :: OS Independent
Classifier: Programming Language :: Python :: 3
Requires-Python: >=3.7
Requires-Dist: flask
Requires-Dist: openai
